dark_web_scraper.py
dark_web_scraper-0.1.dist-info/LICENSE
dark_web_scraper-0.1.dist-info/METADATA
dark_web_scraper-0.1.dist-info/WHEEL
dark_web_scraper-0.1.dist-info/top_level.txt
dark_web_scraper-0.1.dist-info/RECORD
