Metadata-Version: 2.1
Name: dark-web-scraper
Version: 0.1
Summary: A dark web link and image scraper
Home-page: https://github.com/PritamSarbajna/dark-web-scraper
Author: Pritam Sarbajna
License: UNKNOWN
Keywords: darkweb,web scraper,scraper
Platform: UNKNOWN
Classifier: Programming Language :: Python :: 3
Classifier: License :: OSI Approved :: MIT License
Classifier: Operating System :: POSIX :: Linux
Requires-Python: >=3.10
License-File: LICENSE
Requires-Dist: requests
Requires-Dist: fake-useragent
Requires-Dist: beautifulsoup4
